multicombo/__init__.py
multicombo/multicombo.py
multicombo/download/filesize.txt
multicombo-0.8.7.dist-info/LICENSE.txt
multicombo-0.8.7.dist-info/METADATA
multicombo-0.8.7.dist-info/WHEEL
multicombo-0.8.7.dist-info/top_level.txt
multicombo-0.8.7.dist-info/RECORD
