Metadata-Version: 2.1
Name: multicombo
Version: 0.8.7
Summary: Multilingual POS-tagger and Dependency-parser
Home-page: https://github.com/KoichiYasuoka/MultiCOMBO
Author: Koichi Yasuoka
Author-email: yasuoka@kanji.zinbun.kyoto-u.ac.jp
License: GPL
Project-URL: COMBO-pytorch, https://gitlab.clarin-pl.eu/syntactic-tools/combo
Project-URL: Source, https://github.com/KoichiYasuoka/MultiCOMBO
Project-URL: Tracker, https://github.com/KoichiYasuoka/MultiCOMBO/issues
Keywords: NLP Multilingual
Classifier: License :: OSI Approved :: GNU General Public License (GPL)
Classifier: Programming Language :: Python :: 3
Classifier: Operating System :: OS Independent
Classifier: Topic :: Text Processing :: Linguistic
Requires-Python: >=3.6
License-File: LICENSE.txt
Requires-Dist: unidic-combo (>=1.5.4)
